litedict.py
litedict-0.5.dist-info/LICENSE
litedict-0.5.dist-info/METADATA
litedict-0.5.dist-info/WHEEL
litedict-0.5.dist-info/top_level.txt
litedict-0.5.dist-info/RECORD
