Metadata-Version: 2.1
Name: litedict
Version: 0.5
Summary: Simple dictionary built on top of SQLite
Home-page: https://github.com/litements/litedict
Author: Ricardo Ander-Egg Aguilar
Author-email: rsubacc@gmail.com
License: UNKNOWN
Platform: UNKNOWN
Classifier: Operating System :: OS Independent
Requires-Python: >=3.7
License-File: LICENSE
